Workbook
Name aporte: Planilha1!$C$4
Name patrimonio: Planilha1!$C$7
Name qtd_anos: Planilha1!$C$5
Name rendimento_carteira: Planilha1!$J$5
Name salario: Planilha1!$J$4
Name sugestao_investimento: Planilha1!$J$6
Name taxa_mensal: Planilha1!$C$6

Sheet Planilha1
B3: INVESTIMENTO MENSAL | E3: CENÁRIOS | G3: DIVIDENDO | I3: CONFIGURAÇÕES
B4: Quanto investir por mês? | C4: 300 | D4: 2 | E4: Quanto em 2 anos? | F4: =FV(taxa_mensal,$D4*12,aporte*-1) -> 8168.2882 | G4: =F4*rendimento_carteira -> 49.009729 | I4: Salário | J4: 4870
B5: Por quantos anos? | C5: 15 | D5: 5 | E5: Quanto em 5 anos? | F5: =FV(taxa_mensal,$D5*12,aporte*-1) -> 25133.074 | G5: =F5*rendimento_carteira -> 150.79845 | I5: Rendimento Carteiras | J5: 0.006
B6: Taxa de rendimento mensal? | C6: 0.01079 | D6: 10 | E6: Quanto em 10 anos? | F6: =FV(taxa_mensal,$D6*12,aporte*-1) -> 72985.264 | G6: =F6*rendimento_carteira -> 437.91158 | I6: Sugestão de Investimento (30%) | J6: =salario*30% -> 1461
B7: Patrimônio acumulado? | C7: =FV(taxa_mensal,qtd_anos*12,aporte*-1) -> 164093.58 | D7: 20 | E7: Quanto em 20 anos? | F7: =FV(taxa_mensal,$D7*12,aporte*-1) -> 337559.52 | G7: =F7*rendimento_carteira -> 2025.3571
B8: Dividendos mensais? | C8: =patrimonio*rendimento_carteira -> 984.56147 | D8: 30 | E8: Quanto em 30 anos? | F8: =FV(taxa_mensal,$D8*12,aporte*-1) -> 1296650.9 | G8: =F8*rendimento_carteira -> 7779.9054
B11: Perfil | C11: Conservador | E11: Tipo de FII | F11: Percentual Sugerido | G11: Valores
B12: Valor a ser investido por mês | C12: =aporte -> 300 | E12: Papel | F12: =VLOOKUP($C$11&"-"&E12,Planilha2!$A:$D,4,FALSE) -> 0.3 | G12: =F12*$C$12 -> 90
E13: Tijolo | F13: =VLOOKUP($C$11&"-"&E13,Planilha2!$A:$D,4,FALSE) -> 0.5 | G13: =F13*$C$12 -> 150
E14: Híbridos | F14: =VLOOKUP($C$11&"-"&E14,Planilha2!$A:$D,4,FALSE) -> 0.1 | G14: =F14*$C$12 -> 30
E15: FOF's | F15: =VLOOKUP($C$11&"-"&E15,Planilha2!$A:$D,4,FALSE) -> 0.1 | G15: =F15*$C$12 -> 30
E16: Desenvolvimento | F16: =VLOOKUP($C$11&"-"&E16,Planilha2!$A:$D,4,FALSE) -> 0 | G16: =F16*$C$12 -> 0
E17: Hotelarias | F17: =VLOOKUP($C$11&"-"&E17,Planilha2!$A:$D,4,FALSE) -> 0 | G17: =F17*$C$12 -> 0
E18: TOTAL | G18: =SUM(G12:G17) -> 300

Sheet Planilha2
A3: Chave | B3: Perfil | C3: Tipo de FII | D3: %
A4: =B4&"-"&C4 -> Conservador-Papel | B4: Conservador | C4: Papel | D4: 0.3
A5: =B5&"-"&C5 -> Conservador-Tijolo | B5: Conservador | C5: Tijolo | D5: 0.5
A6: =B6&"-"&C6 -> Conservador-Híbridos | B6: Conservador | C6: Híbridos | D6: 0.1
A7: =B7&"-"&C7 -> Conservador-FOF's | B7: Conservador | C7: FOF's | D7: 0.1
A8: =B8&"-"&C8 -> Conservador-Desenvolvimento | B8: Conservador | C8: Desenvolvimento | D8: 0
A9: =B9&"-"&C9 -> Conservador-Hotelarias | B9: Conservador | C9: Hotelarias | D9: 0
A10: =B10&"-"&C10 -> Moderado-Papel | B10: Moderado | C10: Papel | D10: 0.32
A11: =B11&"-"&C11 -> Moderado-Tijolo | B11: Moderado | C11: Tijolo | D11: 0.35
A12: =B12&"-"&C12 -> Moderado-Híbridos | B12: Moderado | C12: Híbridos | D12: 0.08
A13: =B13&"-"&C13 -> Moderado-FOF's | B13: Moderado | C13: FOF's | D13: 0.05
A14: =B14&"-"&C14 -> Moderado-Desenvolvimento | B14: Moderado | C14: Desenvolvimento | D14: 0.1
A15: =B15&"-"&C15 -> Moderado-Hotelarias | B15: Moderado | C15: Hotelarias | D15: 0.1
... A21: =B21&"-"&C21 -> Agressivo-Hotelarias | B21: Agressivo | C21: Hotelarias | D21: 0.1
